cfgparser/__init__.py
cfgparser/config_parser.py
cfgparser/settings.py
cfgparser/io/__init__.py
cfgparser/io/fileloader.py
cfgparser/io/jsonfileloader.py
cfgparser/io/yamlfileloader.py
cfgparser/utils/__init__.py
cfgparser/utils/dynamic_type_loader.py
cfgparser/utils/union_handler.py
cfgparser-1.0.8.dist-info/LICENSE
cfgparser-1.0.8.dist-info/METADATA
cfgparser-1.0.8.dist-info/WHEEL
cfgparser-1.0.8.dist-info/top_level.txt
cfgparser-1.0.8.dist-info/RECORD
