Metadata-Version: 2.1
Name: cfgparser
Version: 1.0.8
Summary: Python package that allows to parse typed configs defined by python dataclasses
Home-page: https://github.com/CaRniFeXeR/PythonConfigParser
Author: Florian Kowarsch
Author-email: flo.kowarsch@yahoo.de
License: UNKNOWN
Project-URL: Bug Reports, https://github.com/CaRniFeXeR/PythonConfigParser/issues
Project-URL: Source, https://github.com/CaRniFeXeR/PythonConfigParser/
Keywords: config,parser,YAML,JSON,typed-parsing,dataclass,lightweight
Platform: UNKNOWN
Classifier: Development Status :: 3 - Alpha
Classifier: Intended Audience :: Developers
Classifier: Topic :: Software Development :: Build Tools
Classifier: License :: OSI Approved :: MIT License
Classifier: Programming Language :: Python :: 3
Classifier: Programming Language :: Python :: 3.7
Classifier: Programming Language :: Python :: 3.8
Classifier: Programming Language :: Python :: 3.9
Classifier: Programming Language :: Python :: 3.10
Classifier: Programming Language :: Python :: 3 :: Only
Requires-Python: >=3.7, <4
